commitexplorer/__init__.py
commitexplorer/client.py
commit_explorer_client-0.2.0.dist-info/LICENSE
commit_explorer_client-0.2.0.dist-info/WHEEL
commit_explorer_client-0.2.0.dist-info/METADATA
commit_explorer_client-0.2.0.dist-info/RECORD
